django_webmonetization/__init__.py
django_webmonetization/middleware.py
django_webmonetization/templatetags/__init__.py
django_webmonetization/templatetags/webmonetization.py
django_webmonetization_martinm10-0.1.3.dist-info/licenses/LICENSE
django_webmonetization_martinm10-0.1.3.dist-info/METADATA
django_webmonetization_martinm10-0.1.3.dist-info/WHEEL
django_webmonetization_martinm10-0.1.3.dist-info/top_level.txt
django_webmonetization_martinm10-0.1.3.dist-info/RECORD
