Metadata-Version: 2.4
Name: django-webmonetization-MartinM10
Version: 0.1.3
Summary: Django integration for Web Monetization
Author-email: Martín Salvachúa <martin.salvachua1@gmail.com>
License-Expression: MIT
Project-URL: Homepage, https://github.com/MartinM10/django-webmonetization
Project-URL: Documentation, https://github.com/MartinM10/django-webmonetization#readme
Project-URL: Issues, https://github.com/MartinM10/django-webmonetization/issues
Classifier: Development Status :: 3 - Alpha
Classifier: Intended Audience :: Developers
Classifier: Operating System :: OS Independent
Classifier: Programming Language :: Python :: 3
Classifier: Programming Language :: Python :: 3.7
Classifier: Programming Language :: Python :: 3.8
Classifier: Programming Language :: Python :: 3.9
Classifier: Framework :: Django
Classifier: Framework :: Django :: 3.2
Classifier: Framework :: Django :: 4.0
Classifier: Framework :: Django :: 4.1
Classifier: Framework :: Django :: 4.2
Requires-Python: >=3.7
License-File: LICENSE
Requires-Dist: Django>=3.2
Dynamic: license-file
